morningstar_fund_scraper/__init__.py
morningstar_fund_scraper/morningstar_fund_scraper.py
morningstar_fund_scraper-0.1.3.dist-info/licenses/LICENSE
morningstar_fund_scraper-0.1.3.dist-info/METADATA
morningstar_fund_scraper-0.1.3.dist-info/WHEEL
morningstar_fund_scraper-0.1.3.dist-info/top_level.txt
morningstar_fund_scraper-0.1.3.dist-info/RECORD
