Metadata-Version: 2.4
Name: morningstar-fund-scraper
Version: 0.1.3
Summary: Add your description here
Requires-Python: >=3.9
License-File: LICENSE
Requires-Dist: ruff>=0.11.10
Dynamic: license-file
